base_folder/__init__.py
base_folder/browser.py
base_folder/definition.py
base_folder/locators.py
pdfconversorcall-0.0.2.dist-info/LICENSE
pdfconversorcall-0.0.2.dist-info/METADATA
pdfconversorcall-0.0.2.dist-info/WHEEL
pdfconversorcall-0.0.2.dist-info/top_level.txt
pdfconversorcall-0.0.2.dist-info/RECORD
