Metadata-Version: 2.1
Name: pdfconversorcall
Version: 0.0.2
Summary: Convert WebElement into pdf
Author: Daniel Rubens
Author-email: danielrubensdaniel@gmail.com
Keywords: python,rpa,robocorp,pdf,html,conversor
Classifier: Development Status :: 1 - Planning
Classifier: Intended Audience :: Developers
Classifier: Programming Language :: Python :: 3
Classifier: Operating System :: Unix
Classifier: Operating System :: MacOS :: MacOS X
Classifier: Operating System :: Microsoft :: Windows
License-File: LICENSE
Requires-Dist: rpaframework
Requires-Dist: robocorp
